{
"type": "FeatureCollection",
"crs": { "type": "name", "properties": { "name": "urn:ogc:def:crs:OGC:1.3:CRS84" } },
                                                                                
"features": [
{ "type": "Feature", "properties": { "index": "18a", "code": "iwd-mj_brw", "title": "icewedgedegradation_mjorgenson_barrow", "source": "Jorgenson et al., no date", "lat": "71.324333", "lon": "-156.6801", "plots": "", "photo": "", "url": "", "detailed_map_url": "", "group": "18", "url_class": "", "img_class": "", "marker-color": "#0000ff" }, "geometry": { "type": "Point", "coordinates": [ -156.6801, 71.324333 ] } },
{ "type": "Feature", "properties": { "index": "18b", "code": "iwd-mj_pru", "title": "icewedgedegradation_mjorgenson_prudhoe", "source": "Jorgenson et al., no date", "lat": "70.225958", "lon": "-148.397", "plots": "", "photo": "", "url": "", "detailed_map_url": "", "group": "18", "url_class": "", "img_class": "", "marker-color": "#0000ff" }, "geometry": { "type": "Point", "coordinates": [ -148.397, 70.225958 ] } },
{ "type": "Feature", "properties": { "index": "18c", "code": "iwd-mj_cr", "title": "icewedgedegradation_mjorgenson_colvilleriver", "source": "Jorgenson et al., no date", "lat": "69.697347", "lon": "-151.5275", "plots": "", "photo": "", "url": "", "detailed_map_url": "", "group": "18", "url_class": "", "img_class": "", "marker-color": "#0000ff" }, "geometry": { "type": "Point", "coordinates": [ -151.5275, 69.697347 ] } },
{ "type": "Feature", "properties": { "index": "18d", "code": "iwd-mj_anwr", "title": "icewedgedegradation_mjorgenson_anwr", "source": "Jorgenson et al., no date", "lat": "70.123387", "lon": "-143.6125", "plots": "", "photo": "", "url": "", "detailed_map_url": "", "group": "18", "url_class": "", "img_class": "", "marker-color": "#0000ff" }, "geometry": { "type": "Point", "coordinates": [ -143.6125, 70.123387 ] } }
]
}
